{
    "client": "Thunder Client",
    "collectionName": "PS_Users",
    "dateExported": "2024-03-03T22:49:10.095Z",
    "version": "1.1",
    "folders": [],
    "requests": [
        {
            "_id": "8baadea4-be4b-4192-8967-2f3edabce1c3",
            "colId": "eb1fe335-21d1-4b9a-b315-0e5d61e11cb2",
            "containerId": "",
            "name": "Register",
            "url": "http://localhost:3000/criticsLy/v1/user/register",
            "method": "POST",
            "sortNum": 10000,
            "created": "2024-03-02T03:07:38.358Z",
            "modified": "2024-03-02T03:24:09.674Z",
            "headers": [],
            "params": [],
            "body": {
                "type": "json",
                "raw": "{\n  \"username\": \"David\",\n  \"email\": \"David@gmail.com\",\n  \"password\": \"12345\"\n}",
                "form": []
            },
            "tests": []
        },
        {
            "_id": "768529a4-72e7-4800-8793-e89939a3c6e5",
            "colId": "eb1fe335-21d1-4b9a-b315-0e5d61e11cb2",
            "containerId": "",
            "name": "Update",
            "url": "http://localhost:3000/criticsLy/v1/user/update",
            "method": "PUT",
            "sortNum": 30000,
            "created": "2024-03-02T03:07:38.359Z",
            "modified": "2024-03-02T03:07:38.359Z",
            "headers": [],
            "params": [],
            "body": {
                "type": "json",
                "raw": "{\n  \"currentPassword\":\"12345\",\n  \"password\":\"12345\",\n  \"username\":\"DieguitoXD\"\n}",
                "form": []
            },
            "tests": []
        }
    ]
}